[
    {
        "audit": false,
        "createable": true,
        "custom": true,
        "customizable": false,
        "dataType": "string",
        "etag": "1e38b4c8-72fa-4831-9908-53f54eeb2a82",
        "fieldLength": 200,
        "fieldOrder": 3,
        "fieldProperties": {
            "autoGenerated": "false"
        },
        "hasIndex": false,
        "isExtended": false,
        "name": "Description",
        "namefield": false,
        "nullable": true,
        "primarykey": false,
        "unique": false,
        "updateable": true
    },
    {
        "audit": false,
        "createable": true,
        "custom": true,
        "customizable": false,
        "dataType": "string",
        "etag": "7e7991bb-8212-495e-aa48-bb7447477fb7",
        "fieldLength": 20,
        "fieldOrder": 5,
        "fieldProperties": {
            "autoGenerated": "false"
        },
        "hasIndex": false,
        "isExtended": false,
        "name": "PID",
        "namefield": false,
        "nullable": false,
        "primarykey": false,
        "unique": true,
        "updateable": true
    },
    {
        "audit": false,
        "createable": true,
        "custom": true,
        "customizable": false,
        "dataType": "string",
        "etag": "2a6a2167-d3cf-4fb6-979a-945f631fd440",
        "fieldLength": 50,
        "fieldOrder": 4,
        "fieldProperties": {
            "autoGenerated": "false"
        },
        "hasIndex": false,
        "isExtended": false,
        "name": "ProcedureType",
        "namefield": false,
        "nullable": true,
        "primarykey": false,
        "unique": false,
        "updateable": true
    },
    {
        "audit": false,
        "createable": true,
        "custom": true,
        "customizable": false,
        "dataType": "string",
        "etag": "ae8f8f32-cd53-4d87-b8dc-181552232b1f",
        "fieldLength": 10,
        "fieldOrder": 1,
        "fieldProperties": {
            "autoGenerated": "false"
        },
        "hasIndex": false,
        "isExtended": false,
        "name": "ProcID",
        "namefield": false,
        "nullable": false,
        "primarykey": true,
        "unique": true,
        "updateable": true
    },
    {
        "audit": false,
        "createable": true,
        "custom": true,
        "customizable": false,
        "dataType": "string",
        "etag": "384c036e-b711-4ceb-8d55-20df465f6f10",
        "fieldLength": 10,
        "fieldOrder": 2,
        "fieldProperties": {
            "autoGenerated": "false"
        },
        "hasIndex": false,
        "isExtended": false,
        "name": "ProcVersion",
        "namefield": false,
        "nullable": false,
        "primarykey": true,
        "unique": true,
        "updateable": true
    },
    {
        "audit": false,
        "createable": true,
        "custom": true,
        "customizable": false,
        "dataType": "date",
        "etag": "01db2516-a3b0-42e0-a406-ed3f162dd5c8",
        "fieldOrder": 6,
        "fieldProperties": {
            "autoGenerated": "false"
        },
        "hasIndex": false,
        "isExtended": false,
        "name": "UpdatedDateTime",
        "namefield": false,
        "nullable": true,
        "primarykey": false,
        "unique": false,
        "updateable": true
    },
    {
        "audit": false,
        "createable": true,
        "custom": true,
        "customizable": false,
        "dataType": "string",
        "etag": "df3fa768-815e-4b7f-8be6-7cb19c17d111",
        "fieldLength": 30,
        "fieldOrder": 7,
        "fieldProperties": {
            "autoGenerated": "false"
        },
        "hasIndex": false,
        "isExtended": false,
        "name": "WRType",
        "namefield": false,
        "nullable": true,
        "primarykey": false,
        "unique": false,
        "updateable": true
    }
]