{
    "admissionPolicy": "no_approval_needed",
    "config": {
        "additional_data": {
            "authorize_request": [
                
            ],
            "profile_request": [
                
            ],
            "refresh_request": [
                
            ],
            "revoke_request": [
                
            ],
            "token_request": [
                
            ]
        },
        "auth_type": "oauth2",
        "authentication_scheme": "header",
        "authorization_endpoint": "https://accounts.google.com/o/oauth2/v2/auth",
        "client_authentication": {
            "authentication_scheme": "header",
            "client_id": "",
            "client_pvt_key_jwt": false,
            "client_secret": ""
        },
        "dependent_providers": [
            
        ],
        "dollarParamPresence": {
            "authorization_endpoint": false,
            "logout_url": false,
            "profile_url": false,
            "revoke_url": false,
            "token_endpoint": false
        },
        "enable_identity_pkce": true,
        "grant_type": "authorization_code",
        "logout_url": "https://accounts.google.com/logout",
        "oauthProviderType": "google",
        "profile": {
            "endpoint": {
                "location": "url",
                "selector": "userinfo_endpoint",
                "type": "indirect",
                "value": "https://accounts.google.com/.well-known/openid-configuration"
            },
            "profile_attribute_selectors": {
                "custom_profile_attribute_selectors": {
                    
                },
                "display_name": "name",
                "email": "email",
                "federation_id": "sub",
                "first_name": "given_name",
                "last_name": "family_name"
            },
            "request_method": "GET"
        },
        "scope": "openid email profile",
        "session_restrictions": {
            "session_restriction_type": "allow_any_number_of_sessions"
        },
        "token_endpoint": "https://www.googleapis.com/oauth2/v4/token"
    },
    "empty": true,
    "identityMeta": {
        "allow_sso": false,
        "oauth2_success_url_config": {
            "allow_any": true,
            "allowed_urls": [
                
            ],
            "default": -1
        }
    },
    "isIntegrityEnabled": true,
    "mapType": "java.util.HashMap",
    "metaPreference": -1,
    "name": "MyNewGoogle",
    "policyConfig": {
        "def_user_status": "pending",
        "max_login_fail": 5
    },
    "ssoenabled": false,
    "type": "oauth2",
    "version": "1.0"
}